neutrapy/__init__.py
neutrapy/__main__.py
neutrapy/args.toml
neutrapy/commands/__init__.py
neutrapy/commands/add.py
neutrapy/commands/build.py
neutrapy/commands/check.py
neutrapy/commands/create.py
neutrapy/commands/remove.py
neutrapy/commands/run.py
neutrapy/commands/sync.py
neutrapy/current_platform_rs.pyi
neutrapy/templates/default/extensions/__init__.py
neutrapy/templates/default/extensions/python/__init__.py
neutrapy/templates/default/extensions/python/__main__.py
neutrapy/templates/default/extensions/python/api.py
neutrapy/templates/default/extensions/python/utils.py
neutrapy/templates/default/neutralino.config.json
neutrapy/templates/default/pyoxidizer.bzl
neutrapy/templates/default/pyproject.toml
neutrapy/templates/default/resources/index.html
neutrapy/templates/default/resources/js/main.js
neutrapy/templates/default/resources/styles.css
neutrapy/utils.py
neutrapy/current_platform_rs.cpython-310-x86_64-linux-gnu.so
neutrapy-0.0.0.dist-info/entry_points.txt
neutrapy-0.0.0.dist-info/WHEEL
neutrapy-0.0.0.dist-info/METADATA
neutrapy-0.0.0.dist-info/RECORD
