Metadata-Version: 2.1
Name: neutrapy
Version: 0.0.0
Summary: Command line tool for build a desktop app using neutralinojs and python
License: MIT
Author: pwwang
Author-email: 1188067+pwwang@users.noreply.github.com
Requires-Python: >=3.8,<4.0
Classifier: License :: OSI Approved :: MIT License
Classifier: Programming Language :: Python :: 3
Classifier: Programming Language :: Python :: 3.10
Classifier: Programming Language :: Python :: 3.8
Classifier: Programming Language :: Python :: 3.9
Requires-Dist: pyparam (>=0.5.3,<0.6.0)
Requires-Dist: rtoml (>=0.8.0,<0.9.0)
